CHANGELOG.txt
LICENSE.txt
MANIFEST.in
README.md
setup.py
coreml/__init__.py
coreml/classification/__init__.py
coreml/classification/models.py
coreml/gradients/README.md
coreml/gradients/__init__.py
coreml/gradients/optimize.py
coreml/gradients/plotting.py
coreml/integerprogramming/__init__.py
coreml/integerprogramming/optimize.py
coreml/integerprogramming/utils.py
coreml/interiorpoint/__init__.py
coreml/interiorpoint/optimize.py
coreml/interiorpoint/plotting.py
coreml/onedimensionaloptimization/__init__.py
coreml/onedimensionaloptimization/optimize.py
coreml/onedimensionaloptimization/plotting.py
coreml/onedimensionaloptimization/utils_onedimensionaloptimization.py
coreml/regression/__init__.py
coreml/regression/models.py
coreml/stochasticoptimization/__init__.py
coreml/stochasticoptimization/models.py
coreml/stochasticoptimization/optimize.py
coreml/stochasticoptimization/plotting.py
coreml/twovarextremas/__init__.py
coreml/twovarextremas/extrema_methods.py
coreml/twovarextremas/find_extrema.py
coreml/twovarextremas/plotting_3d.py
coreml/twovarextremas/utils_twovarextremas.py
mloptima.egg-info/PKG-INFO
mloptima.egg-info/SOURCES.txt
mloptima.egg-info/dependency_links.txt
mloptima.egg-info/requires.txt
mloptima.egg-info/top_level.txt