Metadata-Version: 2.1
Name: mloptima
Version: 0.0.1
Summary: Optimization methods, machine learning tools and models with visualization
Home-page: https://github.com/M1croZavr/ML_opt
Author: Timofey Lashukov
Author-email: tlashukov@gmail.com
License: MIT
Keywords: ml visualization optimization
Platform: UNKNOWN
Classifier: Development Status :: 3 - Alpha
Classifier: Intended Audience :: Education
Classifier: Operating System :: Microsoft :: Windows :: Windows 10
Classifier: Programming Language :: Python :: 3.8
Classifier: License :: OSI Approved :: MIT License
